{
  "2022-11": {
    "name": "Mismagius",
    "percent": 0.42219,
    "usage": 2028,
    "rank": 119
  },
  "2022-12": {
    "name": "Mismagius",
    "percent": 0.11838,
    "usage": 3811,
    "rank": 180
  },
  "2023-01": {
    "name": "Mismagius",
    "percent": 0.61145,
    "usage": 4058,
    "rank": 111
  },
  "2023-02": {
    "name": "Mismagius",
    "percent": 0.08455,
    "usage": 2894,
    "rank": 199
  },
  "2023-03": {
    "name": "Mismagius",
    "percent": 0.13715,
    "usage": 2015,
    "rank": 173
  },
  "2023-04": {
    "name": "Mismagius",
    "percent": 0.10096,
    "usage": 1727,
    "rank": 186
  },
  "2023-05": {
    "name": "Mismagius",
    "percent": 0.14106,
    "usage": 2414,
    "rank": 209
  },
  "2023-06": {
    "name": "Mismagius",
    "percent": 0.06058,
    "usage": 1453,
    "rank": 279
  },
  "2023-07": {
    "name": "Mismagius",
    "percent": 0.07542,
    "usage": 2470,
    "rank": 271
  },
  "2023-08": {
    "name": "Mismagius",
    "percent": 0.05513,
    "usage": 2517,
    "rank": 293
  },
  "2023-09": {
    "name": "Mismagius",
    "percent": 0.07903,
    "usage": 1713,
    "rank": 315
  },
  "2023-09-DLC1": {
    "name": "Mismagius",
    "percent": 0.02947,
    "usage": 979,
    "rank": 366
  },
  "2023-10": {
    "name": "Mismagius",
    "percent": 0.05821,
    "usage": 2483,
    "rank": 321
  },
  "2023-11": {
    "name": "Mismagius",
    "percent": 0.03911,
    "usage": 1668,
    "rank": 334
  },
  "2023-12": {
    "name": "Mismagius",
    "percent": 0.01909,
    "usage": 1117,
    "rank": 442
  },
  "2023-12-DLC2": {
    "name": "Mismagius",
    "percent": 0.01037,
    "usage": 427,
    "rank": 478
  },
  "2024-01": {
    "name": "Mismagius",
    "percent": 0.02293,
    "usage": 1228,
    "rank": 434
  },
  "2024-02": {
    "name": "Mismagius",
    "percent": 0.03395,
    "usage": 1233,
    "rank": 402
  },
  "2024-03": {
    "name": "Mismagius",
    "percent": 0.03587,
    "usage": 1291,
    "rank": 406
  },
  "2024-04": {
    "name": "Mismagius",
    "percent": 0.02461,
    "usage": 1107,
    "rank": 419
  },
  "2024-05": {
    "name": "Mismagius",
    "percent": 0.04265,
    "usage": 819,
    "rank": 372
  },
  "2024-06": {
    "name": "Mismagius",
    "percent": 0.02048,
    "usage": 1051,
    "rank": 420
  }
}