{
  "2022-11": {
    "name": "Bonsly",
    "percent": 0.03527,
    "usage": 204,
    "rank": 287
  },
  "2022-12": {
    "name": "Bonsly",
    "percent": 0.08122,
    "usage": 887,
    "rank": 248
  },
  "2023-01": {
    "name": "Bonsly",
    "percent": 0.07222,
    "usage": 583,
    "rank": 258
  },
  "2023-02": {
    "name": "Bonsly",
    "percent": 0.04891,
    "usage": 284,
    "rank": 286
  },
  "2023-03": {
    "name": "Bonsly",
    "percent": 0.06948,
    "usage": 386,
    "rank": 276
  },
  "2023-04": {
    "name": "Bonsly",
    "percent": 0.04065,
    "usage": 192,
    "rank": 294
  },
  "2023-05": {
    "name": "Bonsly",
    "percent": 0.08291,
    "usage": 386,
    "rank": 300
  },
  "2023-06": {
    "name": "Bonsly",
    "percent": 0.04733,
    "usage": 224,
    "rank": 377
  },
  "2023-07": {
    "name": "Bonsly",
    "percent": 0.11655,
    "usage": 536,
    "rank": 337
  },
  "2023-08": {
    "name": "Bonsly",
    "percent": 0.03126,
    "usage": 150,
    "rank": 397
  },
  "2023-09": {
    "name": "Bonsly",
    "percent": 0.04025,
    "usage": 228,
    "rank": 453
  },
  "2023-09-DLC1": {
    "name": "Bonsly",
    "percent": 0.03295,
    "usage": 107,
    "rank": 469
  },
  "2023-10": {
    "name": "Bonsly",
    "percent": 0.05162,
    "usage": 319,
    "rank": 436
  },
  "2023-11": {
    "name": "Bonsly",
    "percent": 0.05304,
    "usage": 263,
    "rank": 439
  },
  "2023-12": {
    "name": "Bonsly",
    "percent": 0.03624,
    "usage": 156,
    "rank": 542
  },
  "2023-12-DLC2": {
    "name": "Bonsly",
    "percent": 0.04211,
    "usage": 84,
    "rank": 536
  },
  "2024-01": {
    "name": "Bonsly",
    "percent": 0.03295,
    "usage": 162,
    "rank": 560
  },
  "2024-02": {
    "name": "Bonsly",
    "percent": 0.03695,
    "usage": 169,
    "rank": 553
  },
  "2024-03": {
    "name": "Bonsly",
    "percent": 0.04188,
    "usage": 199,
    "rank": 548
  },
  "2024-04": {
    "name": "Bonsly",
    "percent": 0.03945,
    "usage": 177,
    "rank": 546
  },
  "2024-05": {
    "name": "Bonsly",
    "percent": 0.01037,
    "usage": 22,
    "rank": 641
  },
  "2024-06": {
    "name": "Bonsly",
    "percent": 0.02301,
    "usage": 84,
    "rank": 579
  }
}