{
  "elos": [
    "0",
    "1500",
    "1630",
    "1760"
  ],
  "firstMonth": "2022-11",
  "0": {
    "2023-05": {
      "name": "Arceus-Water",
      "percent": 0.029,
      "usage": 135,
      "rank": 387
    },
    "2023-06": {
      "name": "Arceus-Water",
      "percent": 0.68225,
      "usage": 3229,
      "rank": 178
    },
    "2023-07": {
      "name": "Arceus-Water",
      "percent": 0.63579,
      "usage": 2924,
      "rank": 181
    },
    "2023-08": {
      "name": "Arceus-Water",
      "percent": 0.79037,
      "usage": 3792,
      "rank": 166
    },
    "2023-09": {
      "name": "Arceus-Water",
      "percent": 0.76081,
      "usage": 4310,
      "rank": 180
    },
    "2023-09-DLC1": {
      "name": "Arceus-Water",
      "percent": 0.65409,
      "usage": 2124,
      "rank": 200
    },
    "2023-10": {
      "name": "Arceus-Water",
      "percent": 0.57738,
      "usage": 3568,
      "rank": 215
    },
    "2023-11": {
      "name": "Arceus-Water",
      "percent": 0.71815,
      "usage": 3561,
      "rank": 179
    },
    "2023-12": {
      "name": "Arceus-Water",
      "percent": 0.59885,
      "usage": 2578,
      "rank": 214
    },
    "2023-12-DLC2": {
      "name": "Arceus-Water",
      "percent": 0.45123,
      "usage": 900,
      "rank": 265
    },
    "2024-01": {
      "name": "Arceus-Water",
      "percent": 0.54874,
      "usage": 2698,
      "rank": 227
    },
    "2024-02": {
      "name": "Arceus-Water",
      "percent": 0.6686,
      "usage": 3058,
      "rank": 206
    },
    "2024-03": {
      "name": "Arceus-Water",
      "percent": 0.76238,
      "usage": 3623,
      "rank": 185
    },
    "2024-04": {
      "name": "Arceus-Water",
      "percent": 0.9725,
      "usage": 4363,
      "rank": 153
    },
    "2024-05": {
      "name": "Arceus-Water",
      "percent": 1.25736,
      "usage": 2668,
      "rank": 126
    },
    "2024-06": {
      "name": "Arceus-Water",
      "percent": 1.0786,
      "usage": 3938,
      "rank": 142
    }
  },
  "1500": {
    "2023-05": {
      "name": "Arceus-Water",
      "percent": 0.03991,
      "usage": 135,
      "rank": 327
    },
    "2023-06": {
      "name": "Arceus-Water",
      "percent": 0.8908,
      "usage": 3229,
      "rank": 134
    },
    "2023-07": {
      "name": "Arceus-Water",
      "percent": 0.87642,
      "usage": 2924,
      "rank": 136
    },
    "2023-08": {
      "name": "Arceus-Water",
      "percent": 1.14212,
      "usage": 3792,
      "rank": 114
    },
    "2023-09": {
      "name": "Arceus-Water",
      "percent": 1.10929,
      "usage": 4310,
      "rank": 127
    },
    "2023-09-DLC1": {
      "name": "Arceus-Water",
      "percent": 0.95164,
      "usage": 2124,
      "rank": 141
    },
    "2023-10": {
      "name": "Arceus-Water",
      "percent": 0.85924,
      "usage": 3568,
      "rank": 147
    },
    "2023-11": {
      "name": "Arceus-Water",
      "percent": 1.03595,
      "usage": 3561,
      "rank": 121
    },
    "2023-12": {
      "name": "Arceus-Water",
      "percent": 0.86828,
      "usage": 2578,
      "rank": 139
    },
    "2023-12-DLC2": {
      "name": "Arceus-Water",
      "percent": 0.58878,
      "usage": 900,
      "rank": 202
    },
    "2024-01": {
      "name": "Arceus-Water",
      "percent": 0.74272,
      "usage": 2698,
      "rank": 166
    },
    "2024-02": {
      "name": "Arceus-Water",
      "percent": 1.02804,
      "usage": 3058,
      "rank": 132
    },
    "2024-03": {
      "name": "Arceus-Water",
      "percent": 1.09583,
      "usage": 3623,
      "rank": 127
    },
    "2024-04": {
      "name": "Arceus-Water",
      "percent": 1.48404,
      "usage": 4363,
      "rank": 103
    },
    "2024-05": {
      "name": "Arceus-Water",
      "percent": 1.9763,
      "usage": 2668,
      "rank": 78
    },
    "2024-06": {
      "name": "Arceus-Water",
      "percent": 1.70502,
      "usage": 3938,
      "rank": 88
    }
  },
  "1630": {
    "2023-05": {
      "name": "Arceus-Water",
      "percent": 0.07243,
      "usage": 135,
      "rank": 254
    },
    "2023-06": {
      "name": "Arceus-Water",
      "percent": 1.59591,
      "usage": 3229,
      "rank": 71
    },
    "2023-07": {
      "name": "Arceus-Water",
      "percent": 1.97946,
      "usage": 2924,
      "rank": 61
    },
    "2023-08": {
      "name": "Arceus-Water",
      "percent": 2.33021,
      "usage": 3792,
      "rank": 54
    },
    "2023-09": {
      "name": "Arceus-Water",
      "percent": 2.3956,
      "usage": 4310,
      "rank": 56
    },
    "2023-09-DLC1": {
      "name": "Arceus-Water",
      "percent": 1.96429,
      "usage": 2124,
      "rank": 70
    },
    "2023-10": {
      "name": "Arceus-Water",
      "percent": 2.02303,
      "usage": 3568,
      "rank": 65
    },
    "2023-11": {
      "name": "Arceus-Water",
      "percent": 2.14546,
      "usage": 3561,
      "rank": 59
    },
    "2023-12": {
      "name": "Arceus-Water",
      "percent": 1.77714,
      "usage": 2578,
      "rank": 68
    },
    "2023-12-DLC2": {
      "name": "Arceus-Water",
      "percent": 1.0587,
      "usage": 900,
      "rank": 112
    },
    "2024-01": {
      "name": "Arceus-Water",
      "percent": 1.59041,
      "usage": 2698,
      "rank": 78
    },
    "2024-02": {
      "name": "Arceus-Water",
      "percent": 2.42059,
      "usage": 3058,
      "rank": 53
    },
    "2024-03": {
      "name": "Arceus-Water",
      "percent": 2.43219,
      "usage": 3623,
      "rank": 51
    },
    "2024-04": {
      "name": "Arceus-Water",
      "percent": 2.85157,
      "usage": 4363,
      "rank": 44
    },
    "2024-05": {
      "name": "Arceus-Water",
      "percent": 3.99885,
      "usage": 2668,
      "rank": 26
    },
    "2024-06": {
      "name": "Arceus-Water",
      "percent": 3.30971,
      "usage": 3938,
      "rank": 32
    }
  },
  "1760": {
    "2023-05": {
      "name": "Arceus-Water",
      "percent": 0.09265,
      "usage": 135,
      "rank": 169
    },
    "2023-06": {
      "name": "Arceus-Water",
      "percent": 1.84224,
      "usage": 3229,
      "rank": 43
    },
    "2023-07": {
      "name": "Arceus-Water",
      "percent": 3.13004,
      "usage": 2924,
      "rank": 30
    },
    "2023-08": {
      "name": "Arceus-Water",
      "percent": 3.65065,
      "usage": 3792,
      "rank": 28
    },
    "2023-09": {
      "name": "Arceus-Water",
      "percent": 4.17449,
      "usage": 4310,
      "rank": 24
    },
    "2023-09-DLC1": {
      "name": "Arceus-Water",
      "percent": 3.25919,
      "usage": 2124,
      "rank": 32
    },
    "2023-10": {
      "name": "Arceus-Water",
      "percent": 2.79043,
      "usage": 3568,
      "rank": 32
    },
    "2023-11": {
      "name": "Arceus-Water",
      "percent": 3.59996,
      "usage": 3561,
      "rank": 31
    },
    "2023-12": {
      "name": "Arceus-Water",
      "percent": 2.51845,
      "usage": 2578,
      "rank": 41
    },
    "2023-12-DLC2": {
      "name": "Arceus-Water",
      "percent": 1.2138,
      "usage": 900,
      "rank": 61
    },
    "2024-01": {
      "name": "Arceus-Water",
      "percent": 2.54369,
      "usage": 2698,
      "rank": 43
    },
    "2024-02": {
      "name": "Arceus-Water",
      "percent": 3.42818,
      "usage": 3058,
      "rank": 32
    },
    "2024-03": {
      "name": "Arceus-Water",
      "percent": 4.04761,
      "usage": 3623,
      "rank": 27
    },
    "2024-04": {
      "name": "Arceus-Water",
      "percent": 3.05672,
      "usage": 4363,
      "rank": 35
    },
    "2024-05": {
      "name": "Arceus-Water",
      "percent": 5.43281,
      "usage": 2668,
      "rank": 18
    },
    "2024-06": {
      "name": "Arceus-Water",
      "percent": 4.18338,
      "usage": 3938,
      "rank": 24
    }
  }
}