{
  "elos": [
    "0",
    "1500",
    "1630",
    "1760"
  ],
  "firstMonth": "2022-11",
  "0": {
    "2023-06": {
      "name": "Fennekin",
      "percent": 0.0007,
      "usage": 2,
      "rank": 517
    },
    "2023-08": {
      "name": "Fennekin",
      "percent": 0.00329,
      "usage": 7,
      "rank": 462
    },
    "2023-09": {
      "name": "Fennekin",
      "percent": 0.0009,
      "usage": 2,
      "rank": 615
    },
    "2023-11": {
      "name": "Fennekin",
      "percent": 0.006,
      "usage": 16,
      "rank": 510
    },
    "2023-12": {
      "name": "Fennekin",
      "percent": 0.00059,
      "usage": 2,
      "rank": 757
    },
    "2023-12-DLC2": {
      "name": "Fennekin",
      "percent": 0.00058,
      "usage": 1,
      "rank": 727
    },
    "2024-01": {
      "name": "Fennekin",
      "percent": 0.00054,
      "usage": 2,
      "rank": 781
    },
    "2024-02": {
      "name": "Fennekin",
      "percent": 0.00029,
      "usage": 1,
      "rank": 798
    },
    "2024-03": {
      "name": "Fennekin",
      "percent": 0.00366,
      "usage": 14,
      "rank": 633
    },
    "2024-04": {
      "name": "Fennekin",
      "percent": 0.00031,
      "usage": 1,
      "rank": 796
    },
    "2024-05": {
      "name": "Fennekin",
      "percent": 0.00439,
      "usage": 7,
      "rank": 609
    },
    "2024-06": {
      "name": "Fennekin",
      "percent": 0.00469,
      "usage": 14,
      "rank": 634
    }
  },
  "1500": {
    "2023-06": {
      "name": "Fennekin",
      "percent": 0.00032,
      "usage": 2,
      "rank": 510
    },
    "2023-08": {
      "name": "Fennekin",
      "percent": 0.0,
      "usage": 7,
      "rank": 531
    },
    "2023-09": {
      "name": "Fennekin",
      "percent": 0.00064,
      "usage": 2,
      "rank": 574
    },
    "2023-11": {
      "name": "Fennekin",
      "percent": 0.00176,
      "usage": 16,
      "rank": 510
    },
    "2023-12": {
      "name": "Fennekin",
      "percent": 0.00043,
      "usage": 2,
      "rank": 712
    },
    "2023-12-DLC2": {
      "name": "Fennekin",
      "percent": 0.00036,
      "usage": 1,
      "rank": 679
    },
    "2024-01": {
      "name": "Fennekin",
      "percent": 0.00048,
      "usage": 2,
      "rank": 720
    },
    "2024-02": {
      "name": "Fennekin",
      "percent": 0.00017,
      "usage": 1,
      "rank": 765
    },
    "2024-03": {
      "name": "Fennekin",
      "percent": 0.00054,
      "usage": 14,
      "rank": 694
    },
    "2024-04": {
      "name": "Fennekin",
      "percent": 0.00013,
      "usage": 1,
      "rank": 757
    },
    "2024-05": {
      "name": "Fennekin",
      "percent": 0.00341,
      "usage": 7,
      "rank": 546
    },
    "2024-06": {
      "name": "Fennekin",
      "percent": 0.0005,
      "usage": 14,
      "rank": 689
    }
  },
  "1630": {
    "2023-06": {
      "name": "Fennekin",
      "percent": 0.0,
      "usage": 2,
      "rank": 509
    },
    "2023-08": {
      "name": "Fennekin",
      "percent": 0.0,
      "usage": 7,
      "rank": 471
    },
    "2023-09": {
      "name": "Fennekin",
      "percent": 0.0,
      "usage": 2,
      "rank": 635
    },
    "2023-11": {
      "name": "Fennekin",
      "percent": 3e-05,
      "usage": 16,
      "rank": 517
    },
    "2023-12": {
      "name": "Fennekin",
      "percent": 0.0,
      "usage": 2,
      "rank": 780
    },
    "2023-12-DLC2": {
      "name": "Fennekin",
      "percent": 0.0,
      "usage": 1,
      "rank": 721
    },
    "2024-01": {
      "name": "Fennekin",
      "percent": 8e-05,
      "usage": 2,
      "rank": 622
    },
    "2024-02": {
      "name": "Fennekin",
      "percent": 0.0,
      "usage": 1,
      "rank": 794
    },
    "2024-03": {
      "name": "Fennekin",
      "percent": 0.0,
      "usage": 14,
      "rank": 705
    },
    "2024-04": {
      "name": "Fennekin",
      "percent": 0.0,
      "usage": 1,
      "rank": 794
    },
    "2024-05": {
      "name": "Fennekin",
      "percent": 0.00015,
      "usage": 7,
      "rank": 545
    },
    "2024-06": {
      "name": "Fennekin",
      "percent": 1e-05,
      "usage": 14,
      "rank": 632
    }
  },
  "1760": {
    "2023-06": {
      "name": "Fennekin",
      "percent": 0.0,
      "usage": 2,
      "rank": 502
    },
    "2023-08": {
      "name": "Fennekin",
      "percent": 0.0,
      "usage": 7,
      "rank": 469
    },
    "2023-09": {
      "name": "Fennekin",
      "percent": 0.0,
      "usage": 2,
      "rank": 635
    },
    "2023-11": {
      "name": "Fennekin",
      "percent": 0.0,
      "usage": 16,
      "rank": 518
    },
    "2023-12": {
      "name": "Fennekin",
      "percent": 0.0,
      "usage": 2,
      "rank": 777
    },
    "2023-12-DLC2": {
      "name": "Fennekin",
      "percent": 0.0,
      "usage": 1,
      "rank": 718
    },
    "2024-01": {
      "name": "Fennekin",
      "percent": 0.0,
      "usage": 2,
      "rank": 644
    },
    "2024-02": {
      "name": "Fennekin",
      "percent": 0.0,
      "usage": 1,
      "rank": 793
    },
    "2024-03": {
      "name": "Fennekin",
      "percent": 0.0,
      "usage": 14,
      "rank": 719
    },
    "2024-04": {
      "name": "Fennekin",
      "percent": 0.0,
      "usage": 1,
      "rank": 792
    },
    "2024-05": {
      "name": "Fennekin",
      "percent": 1e-05,
      "usage": 7,
      "rank": 516
    },
    "2024-06": {
      "name": "Fennekin",
      "percent": 0.0,
      "usage": 14,
      "rank": 631
    }
  }
}