{
  "2022-11": {
    "name": "Clawitzer",
    "percent": 0.66262,
    "usage": 3833,
    "rank": 130
  },
  "2022-12": {
    "name": "Clawitzer",
    "percent": 0.54481,
    "usage": 5950,
    "rank": 147
  },
  "2023-01": {
    "name": "Clawitzer",
    "percent": 0.60671,
    "usage": 4898,
    "rank": 151
  },
  "2023-02": {
    "name": "Clawitzer",
    "percent": 0.68452,
    "usage": 3975,
    "rank": 141
  },
  "2023-03": {
    "name": "Clawitzer",
    "percent": 0.49353,
    "usage": 2742,
    "rank": 169
  },
  "2023-04": {
    "name": "Clawitzer",
    "percent": 0.44925,
    "usage": 2122,
    "rank": 180
  },
  "2023-05": {
    "name": "Clawitzer",
    "percent": 0.45258,
    "usage": 2107,
    "rank": 188
  },
  "2023-06": {
    "name": "Clawitzer",
    "percent": 0.36595,
    "usage": 1732,
    "rank": 246
  },
  "2023-07": {
    "name": "Clawitzer",
    "percent": 0.32355,
    "usage": 1488,
    "rank": 262
  },
  "2023-08": {
    "name": "Clawitzer",
    "percent": 0.32182,
    "usage": 1544,
    "rank": 266
  },
  "2023-09": {
    "name": "Clawitzer",
    "percent": 0.20353,
    "usage": 1153,
    "rank": 348
  },
  "2023-09-DLC1": {
    "name": "Clawitzer",
    "percent": 0.15459,
    "usage": 502,
    "rank": 364
  },
  "2023-10": {
    "name": "Clawitzer",
    "percent": 0.30455,
    "usage": 1882,
    "rank": 294
  },
  "2023-11": {
    "name": "Clawitzer",
    "percent": 0.35837,
    "usage": 1777,
    "rank": 283
  },
  "2023-12": {
    "name": "Clawitzer",
    "percent": 0.21325,
    "usage": 918,
    "rank": 392
  },
  "2023-12-DLC2": {
    "name": "Clawitzer",
    "percent": 0.20807,
    "usage": 415,
    "rank": 393
  },
  "2024-01": {
    "name": "Clawitzer",
    "percent": 0.13403,
    "usage": 659,
    "rank": 435
  },
  "2024-02": {
    "name": "Clawitzer",
    "percent": 0.18934,
    "usage": 866,
    "rank": 408
  },
  "2024-03": {
    "name": "Clawitzer",
    "percent": 0.26409,
    "usage": 1255,
    "rank": 364
  },
  "2024-04": {
    "name": "Clawitzer",
    "percent": 0.17943,
    "usage": 805,
    "rank": 415
  },
  "2024-05": {
    "name": "Clawitzer",
    "percent": 0.17296,
    "usage": 367,
    "rank": 414
  },
  "2024-06": {
    "name": "Clawitzer",
    "percent": 0.18789,
    "usage": 686,
    "rank": 400
  }
}