{
  "2022-11": {
    "name": "Petilil",
    "percent": 0.00041,
    "usage": 27,
    "rank": 370
  },
  "2022-12": {
    "name": "Petilil",
    "percent": 0.00063,
    "usage": 53,
    "rank": 346
  },
  "2023-01": {
    "name": "Petilil",
    "percent": 0.00039,
    "usage": 24,
    "rank": 393
  },
  "2023-02": {
    "name": "Petilil",
    "percent": 0.00015,
    "usage": 7,
    "rank": 418
  },
  "2023-03": {
    "name": "Petilil",
    "percent": 0.0001,
    "usage": 7,
    "rank": 422
  },
  "2023-04": {
    "name": "Petilil",
    "percent": 0.00012,
    "usage": 24,
    "rank": 414
  },
  "2023-05": {
    "name": "Petilil",
    "percent": 0.00023,
    "usage": 45,
    "rank": 447
  },
  "2023-06": {
    "name": "Petilil",
    "percent": 0.00015,
    "usage": 20,
    "rank": 438
  },
  "2023-07": {
    "name": "Petilil",
    "percent": 9e-05,
    "usage": 7,
    "rank": 478
  },
  "2023-08": {
    "name": "Petilil",
    "percent": 0.0,
    "usage": 18,
    "rank": 504
  },
  "2023-09": {
    "name": "Petilil",
    "percent": 2e-05,
    "usage": 10,
    "rank": 614
  },
  "2023-09-DLC1": {
    "name": "Petilil",
    "percent": 0.0,
    "usage": 1,
    "rank": 620
  },
  "2023-10": {
    "name": "Petilil",
    "percent": 2e-05,
    "usage": 6,
    "rank": 611
  },
  "2023-11": {
    "name": "Petilil",
    "percent": 0.0001,
    "usage": 6,
    "rank": 573
  },
  "2023-12": {
    "name": "Petilil",
    "percent": 1e-05,
    "usage": 8,
    "rank": 748
  },
  "2023-12-DLC2": {
    "name": "Petilil",
    "percent": 0.0,
    "usage": 1,
    "rank": 737
  },
  "2024-01": {
    "name": "Petilil",
    "percent": 1e-05,
    "usage": 2,
    "rank": 759
  },
  "2024-02": {
    "name": "Petilil",
    "percent": 6e-05,
    "usage": 10,
    "rank": 714
  },
  "2024-03": {
    "name": "Petilil",
    "percent": 0.00011,
    "usage": 8,
    "rank": 681
  },
  "2024-04": {
    "name": "Petilil",
    "percent": 6e-05,
    "usage": 9,
    "rank": 724
  },
  "2024-05": {
    "name": "Petilil",
    "percent": 0.00024,
    "usage": 6,
    "rank": 621
  },
  "2024-06": {
    "name": "Petilil",
    "percent": 0.00021,
    "usage": 14,
    "rank": 647
  }
}